PyMCUlib_cpp/__init__.py
PyMCUlib_cpp/blend/__init__.py
PyMCUlib_cpp/blend/blend.py
PyMCUlib_cpp/cam/__init__.py
PyMCUlib_cpp/cam/cam.py
PyMCUlib_cpp/cam/hct.py
PyMCUlib_cpp/cam/hct_solver.py
PyMCUlib_cpp/cam/viewing_conditions.py
PyMCUlib_cpp/contrast/__init__.py
PyMCUlib_cpp/contrast/contrast.py
PyMCUlib_cpp/dislike/__init__.py
PyMCUlib_cpp/dislike/dislike.py
PyMCUlib_cpp/dynamiccolor/__init__.py
PyMCUlib_cpp/dynamiccolor/contrast_curve.py
PyMCUlib_cpp/dynamiccolor/dynamic_color.py
PyMCUlib_cpp/dynamiccolor/dynamic_scheme.py
PyMCUlib_cpp/dynamiccolor/material_dynamic_colors.py
PyMCUlib_cpp/dynamiccolor/tone_delta_pair.py
PyMCUlib_cpp/dynamiccolor/variant.py
PyMCUlib_cpp/palettes/__init__.py
PyMCUlib_cpp/palettes/core.py
PyMCUlib_cpp/palettes/tones.py
PyMCUlib_cpp/quantize/__init__.py
PyMCUlib_cpp/quantize/celebi.py
PyMCUlib_cpp/quantize/lab.py
PyMCUlib_cpp/quantize/wsmeans.py
PyMCUlib_cpp/quantize/wu.py
PyMCUlib_cpp/scheme/__init__.py
PyMCUlib_cpp/scheme/content.py
PyMCUlib_cpp/scheme/expressive.py
PyMCUlib_cpp/scheme/fidelity.py
PyMCUlib_cpp/scheme/fruit_salad.py
PyMCUlib_cpp/scheme/monochrome.py
PyMCUlib_cpp/scheme/neutral.py
PyMCUlib_cpp/scheme/rainbow.py
PyMCUlib_cpp/scheme/tonal_spot.py
PyMCUlib_cpp/scheme/vibrant.py
PyMCUlib_cpp/score/__init__.py
PyMCUlib_cpp/score/score.py
PyMCUlib_cpp/temperature/__init__.py
PyMCUlib_cpp/temperature/temperature_cache.py
PyMCUlib_cpp/utils/__init__.py
PyMCUlib_cpp/utils/image_utils.py
PyMCUlib_cpp/utils/utils.py
pymculib_cpp-1.0.3.dist-info/licenses/LICENSE.md
pymculib_cpp-1.0.3.dist-info/METADATA
pymculib_cpp-1.0.3.dist-info/WHEEL
pymculib_cpp-1.0.3.dist-info/top_level.txt
pymculib_cpp-1.0.3.dist-info/RECORD
