Metadata-Version: 2.4
Name: PyMCUlib_cpp
Version: 1.0.3
Summary: Material Color Utilities Python Library
Home-page: https://github.com/wenkang-deepblue/PyMCUlib-Pythonized-material-color-utilities/tree/main-cpp
Author: Wenkang Li
Author-email: support@deepblue.cc
Classifier: Programming Language :: Python :: 3
Classifier: Programming Language :: Python :: 3.12
Classifier: License :: OSI Approved :: Apache Software License
Classifier: Operating System :: OS Independent
Classifier: Topic :: Software Development :: Libraries
Classifier: Topic :: Multimedia :: Graphics
Requires-Python: >=3.12.0
License-File: LICENSE.md
Requires-Dist: numpy
Requires-Dist: pillow
Dynamic: author
Dynamic: author-email
Dynamic: classifier
Dynamic: description
Dynamic: description-content-type
Dynamic: home-page
Dynamic: license-file
Dynamic: requires-dist
Dynamic: requires-python
Dynamic: summary
